similarities_and_distance_of_soft_sets/__init__.py
similarities_and_distance_of_soft_sets/main.py
hellomilar-0.0.1.dist-info/METADATA
hellomilar-0.0.1.dist-info/WHEEL
hellomilar-0.0.1.dist-info/top_level.txt
hellomilar-0.0.1.dist-info/RECORD
